arg_init-0.0.6.dist-info/METADATA
arg_init-0.0.6.dist-info/WHEEL
arg_init-0.0.6.dist-info/licenses/LICENSE.txt
arg_init/__init__.py
arg_init/_aliases.py
arg_init/_arg.py
arg_init/_arg_defaults.py
arg_init/_arg_init.py
arg_init/_class_arg_init.py
arg_init/_config.py
arg_init/_enums.py
arg_init/_exceptions.py
arg_init/_function_arg_init.py
arg_init/_priority.py
arg_init/_values.py
arg_init/_version.py
arg_init/py.typed
arg_init-0.0.6.dist-info/RECORD
