Metadata-Version: 2.1
Name: arg_init
Version: 0.0.6
Summary: Resolve argument values from arg, env or default values
Keywords: argparse init environment
Author-Email: srfoster65 <135555068+srfoster65@users.noreply.github.com>
License: MIT
Classifier: Programming Language :: Python :: 3
Project-URL: Documentation, https://srfoster65.github.io/arg_init/
Project-URL: Source, https://github.com/srfoster65/arg_init
Requires-Python: >=3.8
Requires-Dist: python-box>=7.0.1
Requires-Dist: pyyaml>=6.0.1
